odoo10_addon_stock_cancel-10.0.0.2.0-py3.8-nspkg.pth
odoo/addons/stock_cancel/README.rst
odoo/addons/stock_cancel/__init__.py
odoo/addons/stock_cancel/__manifest__.py
odoo/addons/stock_cancel/i18n/ca.po
odoo/addons/stock_cancel/i18n/ca_ES.po
odoo/addons/stock_cancel/i18n/de.po
odoo/addons/stock_cancel/i18n/es.po
odoo/addons/stock_cancel/i18n/es_EC.po
odoo/addons/stock_cancel/i18n/it.po
odoo/addons/stock_cancel/i18n/pt.po
odoo/addons/stock_cancel/i18n/stock_cancel.pot
odoo/addons/stock_cancel/images/stock_picking.jpg
odoo/addons/stock_cancel/models/__init__.py
odoo/addons/stock_cancel/models/stock_move.py
odoo/addons/stock_cancel/models/stock_picking.py
odoo/addons/stock_cancel/models/stock_quant.py
odoo/addons/stock_cancel/static/description/icon.png
odoo/addons/stock_cancel/tests/__init__.py
odoo/addons/stock_cancel/tests/test_stock_cancel.py
odoo/addons/stock_cancel/view/stock_view.xml
odoo10_addon_stock_cancel-10.0.0.2.0.dist-info/METADATA
odoo10_addon_stock_cancel-10.0.0.2.0.dist-info/WHEEL
odoo10_addon_stock_cancel-10.0.0.2.0.dist-info/namespace_packages.txt
odoo10_addon_stock_cancel-10.0.0.2.0.dist-info/top_level.txt
odoo10_addon_stock_cancel-10.0.0.2.0.dist-info/RECORD
