Metadata-Version: 2.1
Name: odoo10-addon-stock-cancel
Version: 10.0.0.2.0
Summary: This module allows you to bring back a completed stock picking to draft state
Home-page: http://www.andreacometa.it
Author: www.andreacometa.it,Odoo Community Association (OCA)
Author-email: support@odoo-community.org
License: AGPL-3
Platform: UNKNOWN
Classifier: Programming Language :: Python
Classifier: Framework :: Odoo
Classifier: Framework :: Odoo :: 10.0
Classifier: License :: OSI Approved :: GNU Affero General Public License v3
Requires-Python: ~=2.7
Requires-Dist: odoo10-addon-stock-picking-invoice-link
Requires-Dist: odoo (<10.1dev,>=10.0)
